htmlcrypt/__init__.py
htmlcrypt/__main__.py
htmlcrypt/decrypt.html
htmlcrypt/decrypt.py
htmlcrypt/encrypt.py
htmlcrypt-0.2.2.dist-info/LICENSE
htmlcrypt-0.2.2.dist-info/METADATA
htmlcrypt-0.2.2.dist-info/WHEEL
htmlcrypt-0.2.2.dist-info/entry_points.txt
htmlcrypt-0.2.2.dist-info/top_level.txt
htmlcrypt-0.2.2.dist-info/RECORD
