Metadata-Version: 2.1
Name: htmlcrypt
Version: 0.2.2
Summary: Tool for encrypting HTML files and generating JavaScript to decrypt it
Author: mricherzhagen
License: MIT License
Project-URL: Homepage, https://github.com/mricherzhagen/htmlcrypt
Project-URL: Bug Tracker, https://github.com/mricherzhagen/htmlcrypt/issues
Classifier: Programming Language :: Python :: 3
Classifier: License :: OSI Approved :: MIT License
Classifier: Operating System :: OS Independent
Requires-Python: >=3.9
License-File: LICENSE
Requires-Dist: pycryptodome
